{"id":"20171003_153727_0f37","type":"Feature","geometry":{"coordinates":[[[-71.67262079092053,42.402373887028965],[-71.65004309721108,42.3328177840022],[-71.35911157913672,42.38501328611901],[-71.38204279378523,42.45480588987705],[-71.67262079092053,42.402373887028965]]],"type":"Polygon"},"properties":{"acquired":"2017-10-03T15:37:27.310328Z","anomalous_pixels":0,"cloud_cover":0.01,"ground_control":true,"gsd":3.7,"instrument":"PS2","item_type":"PSScene","pixel_resolution":3,"provider":"planetscope","published":"2021-02-15T15:54:31Z","publishing_stage":"finalized","quality_category":"standard","satellite_azimuth":258.4,"satellite_id":"0f37","strip_id":"807940","sun_azimuth":160.1,"sun_elevation":41.6,"updated":"2021-02-15T15:54:31Z","view_angle":4.1}}
