{"id":"20170622_131301_1_0c75","type":"Feature","geometry":{"coordinates":[[[-71.61608553786897,42.449265894882515],[-71.6747432729666,42.41627565858211],[-71.53179487742163,42.2773449584546],[-71.47339253684412,42.31052150642186],[-71.61608553786897,42.449265894882515]]],"type":"Polygon"},"properties":{"acquired":"2017-06-22T13:13:01.870472Z","anomalous_pixels":0,"cloud_cover":0,"ground_control":true,"gsd":2.9,"instrument":"PS2","item_type":"PSScene","pixel_resolution":3,"provider":"planetscope","published":"2021-02-10T02:55:42Z","publishing_stage":"finalized","quality_category":"standard","satellite_azimuth":178.4,"satellite_id":"0c75","strip_id":"569350","sun_azimuth":95.2,"sun_elevation":41.8,"updated":"2021-02-10T02:55:42Z","view_angle":2.8}}
