{"id":"20180626_145640_101c","type":"Feature","geometry":{"coordinates":[[[-71.69485183198039,42.445040913529965],[-71.67555495507284,42.377996792434026],[-71.39633030675151,42.42240963207426],[-71.41590270884512,42.48942198910281],[-71.69485183198039,42.445040913529965]]],"type":"Polygon"},"properties":{"acquired":"2018-06-26T14:56:40.328648Z","anomalous_pixels":0,"cloud_cover":0,"ground_control":true,"gsd":3.6,"instrument":"PS2","item_type":"PSScene","pixel_resolution":3,"provider":"planetscope","published":"2021-02-25T20:52:24Z","publishing_stage":"finalized","quality_category":"standard","satellite_azimuth":144.1,"satellite_id":"101c","strip_id":"1526950","sun_azimuth":120.4,"sun_elevation":59.9,"updated":"2021-02-25T20:52:24Z","view_angle":0.1}}
