{"id":"20180927_092135_101c","type":"Feature","geometry":{"coordinates":[[[6.942501236572553,49.26615489171441],[6.966077352305908,49.199298335301826],[7.281021941236084,49.24706803978442],[7.257265560254191,49.31391093197715],[6.942501236572553,49.26615489171441]]],"type":"Polygon"},"properties":{"acquired":"2018-09-27T09:21:35.393221Z","anomalous_pixels":0,"clear_confidence_percent":99,"clear_percent":100,"cloud_cover":0,"cloud_percent":0,"ground_control":true,"gsd":3.6,"heavy_haze_percent":0,"instrument":"PS2","item_type":"PSScene","light_haze_percent":0,"pixel_resolution":3,"provider":"planetscope","published":"2021-02-27T10:54:15Z","publishing_stage":"finalized","quality_category":"standard","satellite_azimuth":158.1,"satellite_id":"101c","shadow_percent":0,"snow_ice_percent":0,"strip_id":"1727611","sun_azimuth":143.2,"sun_elevation":32.9,"updated":"2021-02-27T10:54:15Z","view_angle":0.1,"visible_confidence_percent":93,"visible_percent":100}}
