{"id":"20180709_093437_0f44","type":"Feature","geometry":{"coordinates":[[[6.740918427232336,49.24040458787227],[6.764641575785233,49.17341512518263],[7.080033671713609,49.22153571127113],[7.056083656647085,49.28845650573162],[6.740918427232336,49.24040458787227]]],"type":"Polygon"},"properties":{"acquired":"2018-07-09T09:34:37.597154Z","anomalous_pixels":0,"clear_confidence_percent":99,"clear_percent":97,"cloud_cover":0.03,"cloud_percent":3,"ground_control":true,"gsd":3.6,"heavy_haze_percent":0,"instrument":"PS2","item_type":"PSScene","light_haze_percent":0,"pixel_resolution":3,"provider":"planetscope","published":"2021-02-26T02:05:54Z","publishing_stage":"finalized","quality_category":"standard","satellite_azimuth":176.5,"satellite_id":"0f44","shadow_percent":0,"snow_ice_percent":0,"strip_id":"1554156","sun_azimuth":126.8,"sun_elevation":53.8,"updated":"2021-02-26T02:05:54Z","view_angle":0,"visible_confidence_percent":93,"visible_percent":97}}
