{"id":"20190926_134723_1020","type":"Feature","geometry":{"coordinates":[[[-71.81863504442452,42.42608370522129],[-71.79864552361232,42.35835223552078],[-71.51520348713575,42.404418330676215],[-71.53531235487401,42.471889535218416],[-71.81863504442452,42.42608370522129]]],"type":"Polygon"},"properties":{"acquired":"2019-09-26T13:47:23.790242Z","anomalous_pixels":0,"clear_confidence_percent":98,"clear_percent":100,"cloud_cover":0,"cloud_percent":0,"ground_control":true,"gsd":3.6,"heavy_haze_percent":0,"instrument":"PS2","item_type":"PSScene","light_haze_percent":0,"pixel_resolution":3,"provider":"planetscope","published":"2021-03-07T16:12:47Z","publishing_stage":"finalized","quality_category":"test","satellite_azimuth":83.3,"satellite_id":"1020","shadow_percent":0,"snow_ice_percent":0,"strip_id":"2706214","sun_azimuth":127.5,"sun_elevation":32.1,"updated":"2021-03-07T16:12:47Z","view_angle":4,"visible_confidence_percent":98,"visible_percent":100}}
